MANIFEST.in
README.rst
setup.cfg
setup.py
docs/HISTORY.txt
docs/INSTALL.txt
docs/LICENSE.GPL
docs/LICENSE.txt
rt/__init__.py
rt.atmigrator.egg-info/PKG-INFO
rt.atmigrator.egg-info/SOURCES.txt
rt.atmigrator.egg-info/dependency_links.txt
rt.atmigrator.egg-info/entry_points.txt
rt.atmigrator.egg-info/namespace_packages.txt
rt.atmigrator.egg-info/not-zip-safe
rt.atmigrator.egg-info/requires.txt
rt.atmigrator.egg-info/top_level.txt
rt/atmigrator/__init__.py
rt/atmigrator/configure.zcml
rt/atmigrator/i18n.sh
rt/atmigrator/migrator.py
rt/atmigrator/testing.py
rt/atmigrator/browser/__init__.py
rt/atmigrator/browser/configure.zcml
rt/atmigrator/browser/migrate_types.pt
rt/atmigrator/browser/migrate_types.py
rt/atmigrator/locales/rt.atmigrator.pot
rt/atmigrator/locales/it/LC_MESSAGES/rt.atmigrator.po
rt/atmigrator/tests/__init__.py
rt/atmigrator/tests/test_migrator.py
rt/atmigrator/tests/test_view.py