Metadata-Version: 1.1
Name: rt.atmigrator
Version: 0.1.0
Summary: A tool that allows to migrate objects from a content-type to another
Home-page: http://plone.org/products/rt.atmigrator
Author: RedTurtle Technology
Author-email: sviluppoplone@redturtle.it
License: GPL
Keywords: contentmigration migrator plone archetypes
Platform: UNKNOWN
Classifier: Framework :: Plone
Classifier: Framework :: Plone :: 3.3
Classifier: Framework :: Plone :: 4.0
Classifier: Framework :: Plone :: 4.1
Classifier: Framework :: Plone :: 4.2
Classifier: Programming Language :: Python
